MANIFEST.in
README.md
requirements.txt
setup.cfg
setup.py
version.txt
bin/fanalyzer
dativa/analyzer/__init__.py
dativa/analyzer/analyzer.py
dativa/analyzer/autoconfig.py
dativa/analyzer/tests/__init__.py
dativa/analyzer/tests/test_analyser.py
dativa/analyzer/tests/test_autoconfig.py
dativa/analyzer/tests/test-data/analyzer/blank_dirty.csv
dativa/analyzer/tests/test-data/analyzer/blank_test.csv
dativa/analyzer/tests/test-data/analyzer/dates_hour_month.csv
dativa/analyzer/tests/test-data/analyzer/decimal_places.csv
dativa/analyzer/tests/test-data/analyzer/epg-jan-2017.csv
dativa/analyzer/tests/test-data/analyzer/fridge-test-small.csv
dativa/analyzer/tests/test-data/analyzer/no_decimal_places.csv
dativa/analyzer/tests/test-data/analyzer/positive_dirty.csv
dativa/analyzer/tests/test-data/analyzer/session_checking.csv
dativa/analyzer/tests/test-data/analyzer/test_cities_dirty.csv
dativa/analyzer/tests/test-data/analyzer/vod-jun-2017.csv
dativa/scrubber/__init__.py
dativa/scrubber/anonymization.py
dativa/scrubber/base.py
dativa/scrubber/distance.pyx
dativa/scrubber/fallback_addins.py
dativa/scrubber/report.py
dativa/scrubber/scrubber.py
dativa/scrubber/tools.py
dativa/scrubber/validators.py
dativa/scrubber/tests/__init__.py
dativa/scrubber/tests/base_test.py
dativa/scrubber/tests/test_anonymization.py
dativa/scrubber/tests/test_append.py
dativa/scrubber/tests/test_best_match.py
dativa/scrubber/tests/test_date.py
dativa/scrubber/tests/test_lookup.py
dativa/scrubber/tests/test_number.py
dativa/scrubber/tests/test_profile.py
dativa/scrubber/tests/test_session.py
dativa/scrubber/tests/test_skip_blank.py
dativa/scrubber/tests/test_string.py
dativa/scrubber/tests/test_to_text.py
dativa/scrubber/tests/test_unique.py
dativa/scrubber/tests/test_workflow.py
dativa/scrubber/tests/test-data/anonymization/emails.csv
dativa/scrubber/tests/test-data/anonymization/emails_encrypted.csv
dativa/scrubber/tests/test-data/anonymization/emails_hash.csv
dativascrubber.egg-info/PKG-INFO
dativascrubber.egg-info/SOURCES.txt
dativascrubber.egg-info/dependency_links.txt
dativascrubber.egg-info/not-zip-safe
dativascrubber.egg-info/requires.txt
dativascrubber.egg-info/top_level.txt