Metadata-Version: 2.1
Name: dativascrubber
Version: 1.2.141
Summary: Dativa scrubber for automatic file cleansing
Home-page: https://bitbucket.org/deductive/scrubber/
Author: Deductive
Author-email: hello@deductive.com
License: MIT
Keywords: dativa,data cleansing,data pipeline,deductive
Platform: UNKNOWN
Classifier: Development Status :: 5 - Production/Stable
Classifier: Intended Audience :: Developers
Classifier: Topic :: Software Development :: Libraries
Classifier: License :: OSI Approved :: MIT License
Classifier: Programming Language :: Python :: 3.6
